stationreappropriation/__init__.py
stationreappropriation/graphics.py
stationreappropriation/interfaces/demo.py
stationreappropriation/interfaces/facturation.py
stationreappropriation/interfaces/refacturation_turpe.py
stationreappropriation/interfaces/souscriptions.py
stationreappropriation/interfaces/taxes.py
stationreappropriation/marimo_utils.py
stationreappropriation/odoo/__init__.py
stationreappropriation/odoo/odoo_connector.py
stationreappropriation/odoo/services.py
stationreappropriation/scripts/remove_autostart.py
stationreappropriation/scripts/setup_autostart.py
stationreappropriation/scripts/start_marimo.sh
stationreappropriation/utils.py
stationreappropriation-0.5.1.dist-info/LICENSE
stationreappropriation-0.5.1.dist-info/METADATA
stationreappropriation-0.5.1.dist-info/WHEEL
stationreappropriation-0.5.1.dist-info/entry_points.txt
stationreappropriation-0.5.1.dist-info/RECORD
