Metadata-Version: 2.1
Name: stationreappropriation
Version: 0.5.1
Summary: La Station de Réappropriation est un registre centralisé d'outils autonomes, répondant chacun à un besoin spécifique du commun.
License: GPLv3
Author: Virgile Daugé
Author-email: virgile.dauge@pm.me
Requires-Python: >=3.12,<4.0
Classifier: License :: Other/Proprietary License
Classifier: Programming Language :: Python :: 3
Classifier: Programming Language :: Python :: 3.12
Requires-Dist: altair (>=5.4.1,<6.0.0)
Requires-Dist: electriflux (>=0.1.5,<0.2.0)
Requires-Dist: ipython (>=8.29.0,<9.0.0)
Requires-Dist: marimo (>=0.9.9,<0.10.0)
Requires-Dist: matplotlib (>=3.9.2,<4.0.0)
Requires-Dist: pandas (>=2.2.3,<3.0.0)
Requires-Dist: python-dateutil (>=2.9.0.post0,<3.0.0)
Requires-Dist: python-dotenv (>=1.0.1,<2.0.0)
